Workbook

Sheet marriage_halls1
A1: hall_id | B1: name | C1: location | D1: capacity | E1: rent | F1: contact_person | G1: phone_number | H1: email
A2: 1 | B2: Royal Palace | C2: Karachi | D2: 500 | E2: =VLOOKUP(packages!A2,packages!A2:E5,5,FALSE) -> 110000 | F2: Ali Raza | G2: 03111234567 | H2: ali@royalpalace.pk
A3: 1 | B3: Royal Palace | C3: Karachi | D3: 100 | E3: =VLOOKUP(packages!A2,packages!A3:E5,5,FALSE) -> 275000 | F3: Ali Raza | G3: 03111234567 | H3: ali@royalpalace.pk
A4: 1 | B4: Royal Palace | C4: Karachi | D4: 250 | E4: =VLOOKUP(packages!A4,packages!A4:E5,5,FALSE) -> 385000 | F4: Ali Raza | G4: 03111234567 | H4: ali@royalpalace.pk
A5: 1 | B5: Royal Palace | C5: Karachi | D5: 350 | E5: =VLOOKUP(packages!A5,packages!A5:E5,5,FALSE) -> 550000 | F5: Ali Raza | G5: 03111234567 | H5: ali@royalpalace.pk
A6: 2 | B6: Pearl Hall | C6: Lahore | D6: 300 | E6: =VLOOKUP(packages!A6,packages!A6:E8,5,FALSE) -> 170000 | F6: Sana Malik | G6: 03212345678 | H6: sana@pearlhall.pk
A7: 2 | B7: Pearl Hall | C7: Lahore | D7: 100 | E7: =VLOOKUP(packages!A7,packages!A7:E9,5,FALSE) -> 340000 | F7: Sana Malik | G7: 03212345678 | H7: sana@pearlhall.pk
A8: 2 | B8: Pearl Hall | C8: Lahore | D8: 200 | E8: =VLOOKUP(packages!A8,packages!A8:E10,5,FALSE) -> 510000 | F8: Sana Malik | G8: 03212345678 | H8: sana@pearlhall.pk

Sheet booking status
C1: checking booking status
C2: =IF(SUMIFS(hall_availability!D:D, hall_availability!B:B, C5, hall_availability!C:C, D5)=1, "Booked", "Available") -> Available

Sheet hall_availability
A1: availability_id | B1: hall_id | C1: date_available | D1: is_booked
A2: 1 | B2: 1 | C2: 45822 | D2: 0
A3: 2 | B3: 2 | C3: 45823 | D3: 1

Sheet bookings
A1: hall_booking_id | B1: hall_id | C1: customer_name | D1: customer_contact_number | E1: booking_date | F1: status
A2: 1 | B2: 1 | C2: Mufrah Jawaid | D2: 03001234567 | E2: 45822 | F2: confirmation
A3: 2 | B3: 2 | C3: Baasim Ahmed | D3: 03451234567 | E3: 45823 | F3: pending

Sheet customer_bookings
A1: booking_id | B1: hall_id | C1: availability_id | D1: customer_name | E1: customer_phone | F1: customer_email | G1: status
A2: 1 | B2: 1 | C2: 1 | D2: Baasim Ahmed | E2: 03001234567 | F2: baasim@email.com | G2: pending
A3: 2 | B3: 2 | C3: 2 | D3: Mufrah Jawaid | E3: 03451234567 | F3: mufrahjawaid@email.com | G3: confirmation

Sheet hall_expenses
A1: id | B1: hall_id | C1: amount
A2: 1 | B2: 1 | C2: 20000
A3: 2 | B3: 2 | C3: 15000.5

Sheet hall_grocery
A1: grocery_id | B1: hall_id | C1: item | D1: quantity | E1: cost
A2: 1 | B2: 1 | C2: Rice | D2: 50 | E2: 5000
A3: 2 | B3: 2 | C3: Chicken | D3: 30 | E3: 6000

Sheet hall_bills
A1: id | B1: hall_id | C1: bill_type | D1: amount
A2: 1 | B2: 1 | C2: Electricity | D2: 8000
A3: 2 | B3: 2 | C3: Water | D3: 3000

Sheet appointment
A1: appointment_id
A2: 1
A3: 2

Sheet Combined_view
A1: Hall ID | B1: name | C1: location | D1: capacity | E1: rent | F1: contact_person | G1: phone_number | H1: email
A2: 1 | B2: =VLOOKUP(A2,marriage_halls1!$A$1:$H$6,2,FALSE) -> Royal Palace | C2: =VLOOKUP(A2,marriage_halls1!$A$1:$H$6,3,FALSE) -> Karachi | D2: =VLOOKUP(A2,marriage_halls1!$A$1:$H$6,4,FALSE) -> 500 | E2: =VLOOKUP(A2,marriage_halls1!$A$1:$H$6,5,FALSE) -> 110000 | F2: =VLOOKUP(marriage_halls1!A2,marriage_halls1!$A$2:$H$6,6,FALSE) -> Ali Raza | G2: =VLOOKUP(marriage_halls1!A2,marriage_halls1!$A$2:$H$6,7,FALSE) -> 03111234567 | H2: =VLOOKUP(marriage_halls1!A2,marriage_halls1!$A$2:$H$6,8,FALSE) -> ali@royalpalace.pk
A3: 2 | B3: =VLOOKUP(A3,marriage_halls1!$A$1:$H$6,2,FALSE) -> Pearl Hall | C3: =VLOOKUP(A3,marriage_halls1!$A$1:$H$6,3,FALSE) -> Lahore | D3: =VLOOKUP(A3,marriage_halls1!$A$1:$H$6,4,FALSE) -> 300 | E3: =VLOOKUP(A3,marriage_halls1!$A$1:$H$6,5,FALSE) -> 170000 | F3: =VLOOKUP(marriage_halls1!A6,marriage_halls1!$A$2:$H$6,6,FALSE) -> Sana Malik | G3: =VLOOKUP(marriage_halls1!A6,marriage_halls1!$A$2:$H$6,7,FALSE) -> 03212345678 | H3: =VLOOKUP(marriage_halls1!A6,marriage_halls1!$A$2:$H$6,8,FALSE) -> sana@pearlhall.pk

Sheet search halls
C1: search filter by capacity
C2: {=_xlfn._xlws.FILTER(marriage_halls1!A2:G5,marriage_halls1!D2:D5<=100)} -> 1 | D2: Royal Palace | E2: Karachi | F2: 100 | G2: 275000 | H2: Ali Raza | I2: 03111234567
C3: {=_xlfn._xlws.FILTER(marriage_halls1!A2:G5,marriage_halls1!D2:D5<=350)} -> 1 | D3: Royal Palace | E3: Karachi | F3: 100 | G3: 275000 | H3: Ali Raza | I3: 03111234567
C4: 1 | D4: Royal Palace | E4: Karachi | F4: 250 | G4: 385000 | H4: Ali Raza | I4: 03111234567
C5: 1 | D5: Royal Palace | E5: Karachi | F5: 350 | G5: 550000 | H5: Ali Raza | I5: 03111234567
C7: search by price
C8: {=_xlfn._xlws.FILTER(marriage_halls1!A2:E5,marriage_halls1!E2:E5<=550000)} -> 1 | D8: Royal Palace | E8: Karachi | F8: 500 | G8: 110000
C9: 1 | D9: Royal Palace | E9: Karachi | F9: 100 | G9: 275000
C10: 1 | D10: Royal Palace | E10: Karachi | F10: 250 | G10: 385000
C11: 1 | D11: Royal Palace | E11: Karachi | F11: 350 | G11: 550000
C13: search by name
C14: {=_xlfn._xlws.FILTER(marriage_halls1!A2:H8, marriage_halls1!B2:B8 = "royal palace")} -> 1 | D14: Royal Palace | E14: Karachi | F14: 500 | G14: 110000 | H14: Ali Raza | I14: 03111234567 | J14: ali@royalpalace.pk
C15: 1 | D15: Royal Palace | E15: Karachi | F15: 100 | G15: 275000 | H15: Ali Raza | I15: 03111234567 | J15: ali@royalpalace.pk
C16: 1 | D16: Royal Palace | E16: Karachi | F16: 250 | G16: 385000 | H16: Ali Raza | I16: 03111234567 | J16: ali@royalpalace.pk
C17: 1 | D17: Royal Palace | E17: Karachi | F17: 350 | G17: 550000 | H17: Ali Raza | I17: 03111234567 | J17: ali@royalpalace.pk

Sheet packages
A1: hall_id | B1: name | C1: num of person | D1: per head | E1: total package price
A2: 1 | B2: Royal Palace | C2: 100 | D2: 1100 | E2: =C2*D2 -> 110000
A3: 1 | B3: Royal Palace | C3: 250 | D3: 1100 | E3: =C3*D3 -> 275000
A4: 1 | B4: Royal Palace | C4: 350 | D4: 1100 | E4: =C4*D4 -> 385000
A5: 1 | B5: Royal Palace | C5: 500 | D5: 1100 | E5: =C5*D5 -> 550000
A6: 2 | B6: Pearl Hall | C6: 100 | D6: 1700 | E6: =C6*D6 -> 170000
A7: 2 | B7: Pearl Hall | C7: 200 | D7: 1700 | E7: =C7*D7 -> 340000
A8: 2 | B8: Pearl Hall | C8: 300 | D8: 1700 | E8: =C8*D8 -> 510000

Sheet custom packages
A1: hall_id | B1: event_date | C1: customer name | D1: num of person | E1: price acc to per head | F1: catering_price | G1: decoration_price | H1: lighting_price | I1: total_price
A2: 1 | B2: 45823 | C2: Mufrah jawaid | D2: 275 | E2: =D2*packages!D2 -> 302500 | F2: 80000 | G2: 20000 | H2: 10000 | I2: =SUM(D2:H2) -> 412775
A3: 2 | B3: 45823 | C3: Baasim Ahmed | D3: 230 | E3: =D3*packages!D3 -> 253000 | F3: 95000 | G3: 30000 | H3: 15000 | I3: =SUM(D3:H3) -> 393230

Sheet customer cards discount
A1: hall_id | B1: event_date | C1: customer name | D1: Cards name | E1: discount % | F1: total_price | G1: discounted price
A2: 1 | B2: 45823 | C2: Mufrah jawaid | D2: Meezan Gold | E2: 0.2 | F2: 412775 | G2: =F2*0.2 -> 82555
A3: 2 | B3: 45823 | C3: Baasim Ahmed | D3: Meezan Gold | E3: 0.2 | F3: 393230 | G3: =F3*0.2 -> 78646

Sheet valet parking service
A1: hall_id | B1: hall name
A2: 1 | B2: royal palace
A3: 2 | B3: pearl

Sheet check availability
